LICENSE
MANIFEST.in
README.md
setup.py
celery_aide/__init__.py
celery_aide/admin.py
celery_aide/apps.py
celery_aide/celeryconfig.py
celery_aide/conf.py
celery_aide/models.py
celery_aide/signals.py
celery_aide/tasks.py
celery_aide/test_settings.py
celery_aide/tests.py
celery_aide.egg-info/PKG-INFO
celery_aide.egg-info/SOURCES.txt
celery_aide.egg-info/dependency_links.txt
celery_aide.egg-info/requires.txt
celery_aide.egg-info/top_level.txt
celery_aide/migrations/0001_initial.py
celery_aide/migrations/0002_add_created_on.py
celery_aide/migrations/__init__.py